etlwrench/__init__.py
etlwrench/cluster.py
etlwrench/config.py
etlwrench/debug.py
etlwrench/models.py
etlwrench/module.py
etlwrench/node.py
etlwrench/supervisor.py
etlwrench-0.0.4.1.dist-info/LICENSE
etlwrench-0.0.4.1.dist-info/WHEEL
etlwrench-0.0.4.1.dist-info/METADATA
etlwrench-0.0.4.1.dist-info/RECORD
